django_audit_events/__init__.py
django_audit_events/admin.py
django_audit_events/apps.py
django_audit_events/conf.py
django_audit_events/context.py
django_audit_events/filters.py
django_audit_events/middleware.py
django_audit_events/mixin.py
django_audit_events/models.py
django_audit_events/serializers.py
django_audit_events/tasks.py
django_audit_events/urls.py
django_audit_events/utils.py
django_audit_events/version.py
django_audit_events/views.py
django_audit_events/migrations/0001_initial.py
django_audit_events/migrations/0002_archivedauditevent.py
django_audit_events/migrations/0003_auto_20201218_1113.py
django_audit_events/migrations/0004_auto_20210127_2021.py
django_audit_events/migrations/0005_auto_20220215_0756.py
django_audit_events/migrations/0006_auto_20220920_1327.py
django_audit_events/migrations/__init__.py
django_audit_events/tests/__init__.py
django_audit_events/tests/test_conf.py
django_audit_events/tests/test_context.py
django_audit_events/tests/test_middleware.py
django_audit_events/tests/test_mixin.py
django_audit_events/tests/test_models.py
django_audit_events/tests/test_tasks.py
django_audit_events/tests/test_views.py
django_audit_events/tests/urls.py
django_audit_events/tests/utils/__init__.py
django_audit_events/tests/utils/models.py
django_audit_events-0.3.7.dist-info/LICENSE.txt
django_audit_events-0.3.7.dist-info/METADATA
django_audit_events-0.3.7.dist-info/WHEEL
django_audit_events-0.3.7.dist-info/top_level.txt
django_audit_events-0.3.7.dist-info/RECORD
